{"cameraMode":{"drawMode":0,"name":"Shaded","section":"Shading Mode"},"sceneLighting":true,"audioPlay":false,"sceneViewState":{"showFog":true,"showMaterialUpdate":false,"showSkybox":true,"showFlares":true,"showImageEffects":true,"showParticleSystems":true},"in2DMode":false,"pivot":{"x":130.20816040039063,"y":20.3839111328125,"z":-41.736663818359378},"rotation":{"x":0.018224157392978669,"y":-0.9751405715942383,"z":0.2047828733921051,"w":0.08652213960886002},"size":7.1813435554504398,"orthographic":false}